CHANGELOG.txt
LICENCE.txt
MANIFEST.in
README.txt
__init__.py
setup.py
kuldeepcalculator.egg-info/PKG-INFO
kuldeepcalculator.egg-info/SOURCES.txt
kuldeepcalculator.egg-info/dependency_links.txt
kuldeepcalculator.egg-info/top_level.txt
venv/bin/activate_this.py
venv/lib/python3.8/site-packages/_virtualenv.py
venv/lib/python3.8/site-packages/appdirs.py
venv/lib/python3.8/site-packages/contextlib2.py
venv/lib/python3.8/site-packages/distro.py
venv/lib/python3.8/site-packages/easy_install.py
venv/lib/python3.8/site-packages/ipaddr.py
venv/lib/python3.8/site-packages/pyparsing.py
venv/lib/python3.8/site-packages/retrying.py
venv/lib/python3.8/site-packages/six.py
venv/lib/python3.8/site-packages/CacheControl-0.12.6.dist-info/AUTHORS.txt
venv/lib/python3.8/site-packages/CacheControl-0.12.6.dist-info/LICENSE.txt
venv/lib/python3.8/site-packages/CacheControl-0.12.6.dist-info/top_level.txt
venv/lib/python3.8/site-packages/appdirs-1.4.3.dist-info/AUTHORS.txt
venv/lib/python3.8/site-packages/appdirs-1.4.3.dist-info/LICENSE.txt
venv/lib/python3.8/site-packages/appdirs-1.4.3.dist-info/top_level.txt
venv/lib/python3.8/site-packages/cachecontrol/__init__.py
venv/lib/python3.8/site-packages/cachecontrol/_cmd.py
venv/lib/python3.8/site-packages/cachecontrol/adapter.py
venv/lib/python3.8/site-packages/cachecontrol/cache.py
venv/lib/python3.8/site-packages/cachecontrol/compat.py
venv/lib/python3.8/site-packages/cachecontrol/controller.py
venv/lib/python3.8/site-packages/cachecontrol/filewrapper.py
venv/lib/python3.8/site-packages/cachecontrol/heuristics.py
venv/lib/python3.8/site-packages/cachecontrol/serialize.py
venv/lib/python3.8/site-packages/cachecontrol/wrapper.py
venv/lib/python3.8/site-packages/cachecontrol/caches/__init__.py
venv/lib/python3.8/site-packages/cachecontrol/caches/file_cache.py
venv/lib/python3.8/site-packages/cachecontrol/caches/redis_cache.py
venv/lib/python3.8/site-packages/certifi/__init__.py
venv/lib/python3.8/site-packages/certifi/__main__.py
venv/lib/python3.8/site-packages/certifi/core.py
venv/lib/python3.8/site-packages/certifi-2019.11.28.dist-info/AUTHORS.txt
venv/lib/python3.8/site-packages/certifi-2019.11.28.dist-info/LICENSE.txt
venv/lib/python3.8/site-packages/certifi-2019.11.28.dist-info/top_level.txt
venv/lib/python3.8/site-packages/chardet/__init__.py
venv/lib/python3.8/site-packages/chardet/big5freq.py
venv/lib/python3.8/site-packages/chardet/big5prober.py
venv/lib/python3.8/site-packages/chardet/chardistribution.py
venv/lib/python3.8/site-packages/chardet/charsetgroupprober.py
venv/lib/python3.8/site-packages/chardet/charsetprober.py
venv/lib/python3.8/site-packages/chardet/codingstatemachine.py
venv/lib/python3.8/site-packages/chardet/compat.py
venv/lib/python3.8/site-packages/chardet/cp949prober.py
venv/lib/python3.8/site-packages/chardet/enums.py
venv/lib/python3.8/site-packages/chardet-3.0.4.dist-info/AUTHORS.txt
venv/lib/python3.8/site-packages/chardet-3.0.4.dist-info/LICENSE.txt
venv/lib/python3.8/site-packages/chardet-3.0.4.dist-info/entry_points.txt
venv/lib/python3.8/site-packages/chardet-3.0.4.dist-info/top_level.txt
venv/lib/python3.8/site-packages/colorama-0.4.3.dist-info/AUTHORS.txt
venv/lib/python3.8/site-packages/colorama-0.4.3.dist-info/LICENSE.txt
venv/lib/python3.8/site-packages/colorama-0.4.3.dist-info/top_level.txt
venv/lib/python3.8/site-packages/contextlib2-0.6.0.dist-info/AUTHORS.txt
venv/lib/python3.8/site-packages/contextlib2-0.6.0.dist-info/LICENSE.txt
venv/lib/python3.8/site-packages/contextlib2-0.6.0.dist-info/top_level.txt
venv/lib/python3.8/site-packages/distlib-0.3.0.dist-info/AUTHORS.txt
venv/lib/python3.8/site-packages/distlib-0.3.0.dist-info/LICENSE.txt
venv/lib/python3.8/site-packages/distlib-0.3.0.dist-info/top_level.txt
venv/lib/python3.8/site-packages/distro-1.4.0.dist-info/AUTHORS.txt
venv/lib/python3.8/site-packages/distro-1.4.0.dist-info/LICENSE.txt
venv/lib/python3.8/site-packages/distro-1.4.0.dist-info/entry_points.txt
venv/lib/python3.8/site-packages/distro-1.4.0.dist-info/top_level.txt
venv/lib/python3.8/site-packages/html5lib-1.0.1.dist-info/AUTHORS.txt
venv/lib/python3.8/site-packages/html5lib-1.0.1.dist-info/LICENSE.txt
venv/lib/python3.8/site-packages/html5lib-1.0.1.dist-info/top_level.txt
venv/lib/python3.8/site-packages/idna-2.8.dist-info/AUTHORS.txt
venv/lib/python3.8/site-packages/idna-2.8.dist-info/LICENSE.txt
venv/lib/python3.8/site-packages/idna-2.8.dist-info/top_level.txt
venv/lib/python3.8/site-packages/ipaddr-2.2.0.dist-info/AUTHORS.txt
venv/lib/python3.8/site-packages/ipaddr-2.2.0.dist-info/LICENSE.txt
venv/lib/python3.8/site-packages/ipaddr-2.2.0.dist-info/top_level.txt
venv/lib/python3.8/site-packages/lockfile-0.12.2.dist-info/AUTHORS.txt
venv/lib/python3.8/site-packages/lockfile-0.12.2.dist-info/LICENSE.txt
venv/lib/python3.8/site-packages/lockfile-0.12.2.dist-info/top_level.txt
venv/lib/python3.8/site-packages/msgpack-0.6.2.dist-info/AUTHORS.txt
venv/lib/python3.8/site-packages/msgpack-0.6.2.dist-info/LICENSE.txt
venv/lib/python3.8/site-packages/msgpack-0.6.2.dist-info/top_level.txt
venv/lib/python3.8/site-packages/packaging-20.3.dist-info/AUTHORS.txt
venv/lib/python3.8/site-packages/packaging-20.3.dist-info/LICENSE.txt
venv/lib/python3.8/site-packages/packaging-20.3.dist-info/top_level.txt
venv/lib/python3.8/site-packages/pep517-0.8.2.dist-info/AUTHORS.txt
venv/lib/python3.8/site-packages/pep517-0.8.2.dist-info/LICENSE.txt
venv/lib/python3.8/site-packages/pep517-0.8.2.dist-info/top_level.txt
venv/lib/python3.8/site-packages/pip-20.0.2.dist-info/LICENSE.txt
venv/lib/python3.8/site-packages/pip-20.0.2.dist-info/entry_points.txt
venv/lib/python3.8/site-packages/pip-20.0.2.dist-info/top_level.txt
venv/lib/python3.8/site-packages/pkg_resources-0.0.0.dist-info/AUTHORS.txt
venv/lib/python3.8/site-packages/pkg_resources-0.0.0.dist-info/LICENSE.txt
venv/lib/python3.8/site-packages/progress-1.5.dist-info/AUTHORS.txt
venv/lib/python3.8/site-packages/progress-1.5.dist-info/LICENSE.txt
