Metadata-Version: 1.0
Name: kuldeepcalculator
Version: 0.0.2
Summary: A baisc calulcator
Home-page: UNKNOWN
Author: kuldeep khatana
Author-email: kuldeep.si.softprodigy@gmail.com
License: UNKNOWN
Keywords: calulcator
Platform: UNKNOWN
